README.md
setup.py
helium/__init__.py
helium.egg-info/PKG-INFO
helium.egg-info/SOURCES.txt
helium.egg-info/dependency_links.txt
helium.egg-info/not-zip-safe
helium.egg-info/requires.txt
helium.egg-info/top_level.txt
helium/_impl/__init__.py
helium/_impl/match_type.py
helium/_impl/selenium_wrappers.py
helium/_impl/util/__init__.py
helium/_impl/util/dictionary.py
helium/_impl/util/geom.py
helium/_impl/util/html.py
helium/_impl/util/inspect_.py
helium/_impl/util/lang.py
helium/_impl/util/path.py
helium/_impl/util/system.py
helium/_impl/util/xpath.py